Metadata-Version: 2.2
Name: pyvkfft
Version: 2025.1.1
Summary: Python wrapper for the CUDA and OpenCL backends of VkFFT,providing GPU FFT for PyCUDA, PyOpenCL and CuPy
Home-page: https://github.com/vincefn/pyvkfft
Author: Vincent Favre-Nicolin
Author-email: favre@esrf.fr
License: MIT License
Project-URL: Source, https://github.com/vincefn/pyvkfft
Project-URL: Documentation, https://pyvkfft.readthedocs.io/
Project-URL: Bug Tracker, https://github.com/vincefn/pyvkfft/issues
Project-URL: VkFFT project, https://github.com/DTolm/VkFFT
Classifier: Programming Language :: Python :: 3
Classifier: License :: OSI Approved :: MIT License
Classifier: Operating System :: OS Independent
Classifier: Environment :: GPU
License-File: LICENSE
Requires-Dist: numpy
Requires-Dist: psutil
Requires-Dist: pyopencl
Provides-Extra: doc
Requires-Dist: sphinx; extra == "doc"
Requires-Dist: nbsphinx; extra == "doc"
Requires-Dist: nbsphinx-link; extra == "doc"
Requires-Dist: sphinx-argparse; extra == "doc"
Requires-Dist: sphinx-rtd-theme; extra == "doc"
Dynamic: author
Dynamic: author-email
Dynamic: classifier
Dynamic: description
Dynamic: home-page
Dynamic: license
Dynamic: project-url
Dynamic: provides-extra
Dynamic: requires-dist
Dynamic: summary
